jianshou/__init__.py
jianshou/api.py
jianshou_client-1.0.1.dist-info/LICENSE
jianshou_client-1.0.1.dist-info/METADATA
jianshou_client-1.0.1.dist-info/WHEEL
jianshou_client-1.0.1.dist-info/top_level.txt
jianshou_client-1.0.1.dist-info/RECORD
